README.md
setup.py
Arm_Lib/Arm_Lib.py
Arm_Lib/__init__.py
Arm_lib.egg-info/PKG-INFO
Arm_lib.egg-info/SOURCES.txt
Arm_lib.egg-info/dependency_links.txt
Arm_lib.egg-info/top_level.txt